socialize/__init__.py
socialize/core.py
socialize/forms.py
socialize/models.py
socialize/social.py
socialize/stream.py
socialize/urls.py
socialize/views.py
socialize/migrations/0001_initial.py
socialize/migrations/__init__.py
django_socialize-0.5.4.dist-info/LICENSE
django_socialize-0.5.4.dist-info/METADATA
django_socialize-0.5.4.dist-info/WHEEL
django_socialize-0.5.4.dist-info/top_level.txt
django_socialize-0.5.4.dist-info/RECORD
