Metadata-Version: 2.1
Name: django-socialize
Version: 0.5.4
Summary: A Django app to create social networks with social authentication.
Home-page: https://williamlagos.github.io/
Author: William Oliveira de Lagos
Author-email: william.lagos@icloud.com
License: LGPLv3 License
Platform: UNKNOWN
Classifier: Environment :: Web Environment
Classifier: Framework :: Django
Classifier: Intended Audience :: Developers
Classifier: License :: OSI Approved :: BSD License
Classifier: Operating System :: OS Independent
Classifier: Programming Language :: Python
Classifier: Programming Language :: Python :: 2
Classifier: Programming Language :: Python :: 2.7
Classifier: Topic :: Internet :: WWW/HTTP
Classifier: Topic :: Internet :: WWW/HTTP :: Dynamic Content
